Workbook

Sheet Sheet1
A1: Status | B1: Order Type | C1: Service Type | D1: Contact Person | E1: Contact Number | F1: Contact Email | G1: Company Name | H1: Standardized Company Name | I1: Product Subscribe | J1: Billing Account / Master Account | K1: Account/Root ID UID | L1: Account Name | M1: Account Login Email | N1: Password | O1: Billing Address | P1: Other Account Information | Q1: SRD | R1: Order Receive Date | S1: CxS Complete Date | T1: Service No. | U1: CxS Request No. | V1: TID | W1: OASIS Number | X1: SD Number | Y1: Remark | Z1: PS Job | AA1: T2/ T3 | AB1: Welcome Letter | AC1: By | AD1: Order Form
A2: Completed | D2: Ron Ko | E2: 23038766 | G2: WING FUNG REALTY INVESTMENT LIMITED | H2: =IFERROR(VLOOKUP(G2, Sheet2!$A:$B, 2, FALSE), A2) -> WING FUNG REALTY INVESTMENT LIMITED | I2: AWS (Amazon Web Service) | M2: infrastructure@wfgold.com | N2: 3txj18487i | Q2: 43885 | S2: 43885 | T2: CL554098 | U2: 393444/1-2 | V2: 102318
A3: Completed | D3: Ron Ko | E3: 23038766 | G3: WING FUNG REALTY INVESTMENT LIMITED | H3: =IFERROR(VLOOKUP(G3, Sheet2!$A:$B, 2, FALSE), A3) -> WING FUNG REALTY INVESTMENT LIMITED | I3: Alibaba Cloud | K3: 5794684087356582 | M3: it0001@wfgold.com | Q3: 44092 | S3: 44123 | T3: CL544006 | U3: 149525/1-2 | V3: 102456 | Y3: [19-Oct-2020] Linking is completed. Request to amended SRD to 19-Oct-2020 by Ann. [22-Oct-2020] Checked SRD not update yet. Sent email to Sammy [23-Oct-2020] Sammy confirmed no need to change SRD as no contract boundary. Completed order in CxS with SRD on 19-Oct-20 [28-Apr-2021] Migration request from Zens to B-Data by Thomas [17-Jul-2021] Bdata updaed that migration completed | Z3: N | AA3: 1 | AC3: Ann
A4: Completed | D4: Ron Ko | E4: 23038766 | F4: ronko@wfgold.com | G4: WING FUNG PRECIOUS METALS LIMITED | H4: =IFERROR(VLOOKUP(G4, Sheet2!$A:$B, 2, FALSE), A4) -> WING FUNG PRECIOUS METALS LIMITED | I4: AWS (Amazon Web Service) | J4: infrastructure@wfgold.com | K4: 169239530719 | L4: pm_infra@wfgold.com | M4: pm_infra@wfgold.com | Q4: 44042 | S4: 44042 | T4: CL559730 | U4: RN640134/1-2 | V4: 102432 | Y4: [29-Jul-20] Submitted request to Ingram. Cus accepted. Pending for cloud checkr setup [4-Aug-20] Completed in CxS with completion date on 30-Jul-20 [16-Sep-20] checked no consumption yet [9-Oct-2020] Billing account setup under | AB4: Yes
A5: Completed | D5: Ron Ko | E5: 23038766 | G5: WING FUNG FUTURES LIMITED | H5: =IFERROR(VLOOKUP(G5, Sheet2!$A:$B, 2, FALSE), A5) -> WING FUNG FUTURES LIMITED | I5: AWS (Amazon Web Service) | K5: 974644219856 | M5: fu_infra@wfgold.com | Q5: 44047 | S5: 44047 | T5: CL559699 | U5: 652533/1-2 | V5: 102430 | Y5: [30-Jul-20] Submitted request to Ingram. [31-Jul-20]Cus accepted. Penidng for cloud checkr setup [4-Aug-20] Completed in CxS with completion date on 4-Aug-20 [10-Aug-20] Added in cloudcheckr
A6: Completed | D6: Ron Ko | E6: 23038766 | F6: Customer contact : ronko@wfgold.com | G6: WING FUNG BULLION INVESTMENT LIMITED | H6: =IFERROR(VLOOKUP(G6, Sheet2!$A:$B, 2, FALSE), A6) -> WING FUNG BULLION INVESTMENT LIMITED | I6: AWS (Amazon Web Service) | K6: 875512351873 | M6: Login account : bi_infra@wfgold.com Password : s9r5k5ea8y | P6: Root Login : bi_infra@wfgold.com | Q6: 43902 | S6: 43909 | T6: CL557680 | U6: 795404/1-2 | V6: 102336 | Y6: Customer contact : ronko@wfgold.com 875512351873 Root Login : bi_infra@wfgold.com [19-Mar-2020] Customer accepted invitation on. Case completed in CxS with completion date on 19-Mar-2020 [4-Jun-2020] moved to Ingram Micro on 1-Jun and added into HKT family on 4-Jun.
A7: Completed | D7: Brian Yeung | E7: 22129233 / 60634889 | F7: CUS Email : Brian.C.Yeung@honourprinting.com | G7: UMADX ONLINE (MALAYSIA) SDN. BHD | H7: =IFERROR(VLOOKUP(G7, Sheet2!$A:$B, 2, FALSE), A7) -> UMADX ONLINE (MALAYSIA) SDN. BHD | I7: Microsoft Azure | M7: Tenant ID : umadxonline.onmicrosoft.com | O7: Address: 15/F MAGNET PLACE TOWER 1, 77-81 CONTAINER PORT ROAD, KWAI CHUNG NEW TERRITORIES | Q7: 44055 | S7: 44050 | T7: CL541911 | U7: 503074/1-2 | V7: 102438 | Y7: Address: 15/F MAGNET PLACE TOWER 1, 77-81 CONTAINER PORT ROAD, KWAI CHUNG NEW TERRITORIES CUS Email : Brian.C.Yeung@honourprinting.com [7-Aug-2020] Acc created. Pass logn to sales.Welcome letter sent. Completed in CxS.
A8: Completed | D8: Davy Liu | E8: 28302631 / 90255571 | G8: TYSAN MANAGEMENT LIMITED | H8: =IFERROR(VLOOKUP(G8, Sheet2!$A:$B, 2, FALSE), A8) -> TYSAN MANAGEMENT LIMITED | I8: AWS (Amazon Web Service) | K8: 87697955396 | M8: Root Login : davyliu@tysan.com | Q8: 43977 | S8: 43983 | T8: CL545361 | U8: RN148163/1-2 | V8: 102382 | Y8: [20-May-2020] Submitted request to Ingram. Pending for their reply. [28-May-2020] Customer accepted invitation. Waiting for Ingram to add account into cloud checkr [1-Jun-2020] Cloud Checkr set up completed. Case completed in SRS.
A9: Completed | D9: Kevin Chan | E9: 25962878 / 62888721 | F9: Cus contact: kevinchan@travelsky.com.hk | G9: TRAVELSKY TECHNOLOGY (HONGKONG) LTD. | H9: =IFERROR(VLOOKUP(G9, Sheet2!$A:$B, 2, FALSE), A9) -> TRAVELSKY TECHNOLOGY (HONGKONG) LTD. | I9: Google Cloud Platform (GCP) | M9: Root Login: darasakor@travelsky.com.hk | Q9: 44053 | S9: 44054 | T9: CL540961 | U9: 932200/1-2 | V9: 102442 | Y9: Cus contact: kevinchan@travelsky.com.hk [7-Aug-2020]Billing Account creatd and pendng for customer linking acc to HKT. [11-Aug-20] Customer complete linking to HKT. Complete order in CxS with completion date 11-Aug. Welcome letter sent
A10: Completed | D10: Eddy Fung | E10: 2402 6400 / 91798730 | G10: Techtronic Industries Co. Ltd | H10: =IFERROR(VLOOKUP(G10, Sheet2!$A:$B, 2, FALSE), A10) -> Techtronic Industries Co. Ltd | I10: AWS (Amazon Web Service) | K10: 765879711441 | L10: Techtronic Industries Co. Ltd | M10: Root email: aws.hkt@tti.com.hk | O10: Addr3ess: 28/F, Tower 2, KCC, Kwai Chung, NT | Q10: 43591 | S10: 44298 | T10: CL542277 | U10: 731246/3-4 | V10: 101990 | Y10: Provisioned originally by Ann Li ( @ ecloudvalley ) Addr3ess: 28/F, Tower 2, KCC, Kwai Chung, NT [9-Apr-2021] Consultant Tony request to link up with ingram Micro due to cus accidentally quit ecloudvalley. [ cus didn't migrate to ingram micro at the time of changing vendor ] . Submitted request w/o address to ingram micro due to urgency. [10-Apr-2021] Ingram micro sent invitation to cus and cus accepted. [12-Apr-2021] Pending for usage for issue welcome letter [20-Apr-2021] Checked usage on 12-Apr-2021. Welcom letter sent | Z10: N
A11: Completed | D11: Federick Alex (Admin ) / Kenny Chan (IT) | E11: 27938887 / 26938891 | G11: SOFI SECURITIES LIMITED (SOFI SERVICES ( HONG KONG ) LTD) | H11: =IFERROR(VLOOKUP(G11, Sheet2!$A:$B, 2, FALSE), A11) -> SOFI SECURITIES LIMITED (SOFI SERVICES ( HONG KONG ) LTD) | I11: Alibaba Cloud | K11: 5497093001888295 | Q11: 44027 | S11: 44027 | T11: CL555456 | V11: 102198 | Y11: REMARK: Change register name from 8 securites Ltd to Sofi Services (Hong Kong) ltd ( Change of company name order only ) [21-Sep-2020] completed order in CxS with SRD on 15-Jul-2020
A12: Completed | D12: BEN SZE | E12: 23139152 / 62772626 | G12: PROFIT CHART DEVELOPMENT LIMITED | H12: =IFERROR(VLOOKUP(G12, Sheet2!$A:$B, 2, FALSE), A12) -> PROFIT CHART DEVELOPMENT LIMITED | I12: AWS (Amazon Web Service) | K12: 812560180108 | M12: Root Login: mis@newaykb.com.hk | O12: Address : Flat 801, 8/F, East Ocean Cente, 98 Granvielle Road, Tst | Q12: 44096 | S12: 44097 | T12: CL543893 | U12: 157216/1-2 | V12: 102460 | Y12: Address : Flat 801, 8/F, East Ocean Cente, 98 Granvielle Road, Tst [18-Sep-2020] submitted request to ingram. Pending for ingram reply. [22-Sep-2020] Cus accepted invitation ( Thomas provide screen cap ). Completed order in CxS. Pending for cloud checkr setup [25-Sep-2020] Cloudcheckr setuip completed. | Z12: N
A13: Completed | D13: Jessie Li / Hugo Choi | E13: 9022 5988 / 9357 4353 | F13: =F15 -> 0 | G13: ORANGE DATA LIMITED (Chnaged ASCENTAS CAPITAL MANAGEMENT LIMITED) | H13: =IFERROR(VLOOKUP(G13, Sheet2!$A:$B, 2, FALSE), A13) -> ASCENTAS CAPITAL MANAGEMENT LIMITED | I13: Alibaba Cloud | K13: 5864600931668619 | M13: Link Email : infra.consult@pgpg.la | Q13: 44119 | S13: 44117 | T13: CL544854 | U13: 499248/1-2 | V13: 102472 | Y13: Provisioned by Ann Li [12-Nov-20] Ann updated that the case was completed on 13-Oct. Completed in CxS with completion date on 13-Oct-20. [28-Apr-2021] Migration request from Zens to B-Data by Thomas [2-Jun-2021] Migraion completed on 2-Jun-2021. | Z13: N
A14: Completed | D14: Cheng Ping Wai | E14: 27938376 / 98522884 | F14: pw.cheng@leverstyle.com | G14: LEVER SHIRT LIMITED | H14: =IFERROR(VLOOKUP(G14, Sheet2!$A:$B, 2, FALSE), A14) -> LEVER SHIRT LIMITED | I14: Microsoft Azure | Q14: 43830 | S14: 43909 | T14: CL547226 | U14: 954467/1-2 | V14: 102340 | Y14: backdate order. [19-Mar-2020] Peter replied that the service has been provisioned. Case completedin CxS with completion date on 19-Mar-2020.
A15: Completed | D15: Dick Tong | E15: 28999467 / 90256906 | G15: LEIGH & ORANGE LTD | H15: =IFERROR(VLOOKUP(G15, Sheet2!$A:$B, 2, FALSE), A15) -> LEIGH & ORANGE LTD | I15: AWS (Amazon Web Service) | K15: 320298981373 | M15: Login account : itadmin@leighorange.com Password : pq2s5gy0jf | Q15: 43852 | S15: 43892 | T15: CL548876 | U15: 663268/1-2 | V15: 102302 | Y15: AWS Account ID: 320298981373 Root Login : itadmin@leighorange.com [2-Mar-2020] completed in CxS.
A16: Completed | G16: LEGAL AID DEPT | H16: =IFERROR(VLOOKUP(G16, Sheet2!$A:$B, 2, FALSE), A16) -> LEGAL AID DEPT | I16: Google Cloud Platform (GCP) | Q16: 43741 | T16: CL552465 | U16: 919068/1-2 | V16: 102190 | Y16: Revised SRD from 3-Oct to 27-Sep by ordering team (SP handle by product team)
A17: Completed | D17: Randy Mark | E17: 39745607 / 60110033 | F17: Cutomer email: rmark@kbquest.com | G17: KBQUEST HONG KONG LIMITED OGCIO | H17: =IFERROR(VLOOKUP(G17, Sheet2!$A:$B, 2, FALSE), A17) -> KBQUEST HONG KONG LIMITED OGCIO | I17: Microsoft Azure | M17: Tenant ID : ogciosmartlampost.onmicrosoft.com | Q17: 44047 | S17: 44047 | T17: CL559571 | U17: 048802/1-2 | V17: 102428 | Y17: Cutomer email: rmark@kbquest.com [31-Jul-20] Product Peter replied that no need to provision for this customer as they will take over the existing tenant of OGCIO (Customer name in CSP : Office of the Government Chief Information Officer) Remark: Call in on behalf of OGCIO [4-Aug-20] Completed in CxS with completion date on 4-Aug
A18: Completed | D18: Tony Cheng / Ringo Lau | E18: 27820875/ 27827533 | F18: ringolau@takhk.com | G18: ITAK (INTERNATIONAL) LIMITED | H18: =IFERROR(VLOOKUP(G18, Sheet2!$A:$B, 2, FALSE), A18) -> ITAK (INTERNATIONAL) LIMITED | I18: Microsoft Azure | Q18: 43930 | S18: 43930 | T18: CL541269 | U18: 671011/1-2 | V18: 102354 | Y18: [7-Apr-2020] Peter has provisioned the service for customer.
A19: Completed | D19: Mr Brian Yeung | E19: 22129233 / 60634889 | F19: CUS Email : Brian.C.Yeung@honourprinting.com | G19: HONOUR MAILING AND PRINTING LTD | H19: =IFERROR(VLOOKUP(G19, Sheet2!$A:$B, 2, FALSE), A19) -> HONOUR MAILING AND PRINTING LTD | M19: Tenant ID : umadxonline.onmicrosoft.com | O19: Address: 15/F MAGNET PLACE TOWER 1, 77-81 CONTAINER PORT ROAD, KWAI CHUNG NEW TERRITORIES | Q19: 44061 | S19: 44109 | T19: CL550279 | U19: 78673/1-2 | V19: 102446 | Y19: Address: 15/F MAGNET PLACE TOWER 1, 77-81 CONTAINER PORT ROAD, KWAI CHUNG NEW TERRITORIES CUS Email : Brian.C.Yeung@honourprinting.com PS job order ( refer to CL541911 ) [7-Sep-2020] Sent email to Peter for update [16-Sep-2020] sent email for update again [5-Oct-2020] AM Ceilia confrimed all job completed. completed CxS order with completiondate on 5-Oct-2020. | Z19: Y
A20: Completed | D20: Albert Cheng | E20: 2260 3499 / 9681 3499 | F20: Contact Email : albert.cheng@haesl.com | G20: HONG KONG AERO ENGINE SERVICES LTD | H20: =IFERROR(VLOOKUP(G20, Sheet2!$A:$B, 2, FALSE), A20) -> HONG KONG AERO ENGINE SERVICES LTD | I20: AWS (Amazon Web Service) | K20: 146909753979 | M20: Root Login :tech.team@haesl.com | Q20: 44021 | S20: 44025 | T20: CL550611 | U20: RN492408/1-2 | V20: 102408 | Y20: Contact Email : albert.cheng@haesl.com [7-Jul-2020] Submitted request to Ingram. Pending for their reply. [8-Jul-2020] Customer accepted invitation and completed orderin CxS. [8-Jul-2020] pending for ingram to consolidate billing to cloud checkr [13-Jul-2020] Cloud checkr setup completed. [13-Aug-2020] Add once off charge order RN089097/1-2 for PS job
A21: Completed | D21: Albert Cheng | E21: 2260 3499 / 9681 3499 | G21: HONG KONG AERO ENGINE SERVICES LTD | H21: =IFERROR(VLOOKUP(G21, Sheet2!$A:$B, 2, FALSE), A21) -> HONG KONG AERO ENGINE SERVICES LTD | Q21: 44056 | S21: 44055 | T21: CL550611 | U21: RN089097/1-2 | V21: 102408 | Y21: Remark: PS job order of RN492408/1-2 [7-Sep-2020] Updated from PS team Lok that PS job was completed on 15-Jul-2020. Case completed in CxS with completion date on 12-Aug-2020 | Z21: Y
A22: Completed | D22: Roger Ng | F22: roger.kw.ng@pccw.com | G22: HKT Limited ( HKT Wireless Business ) | H22: =IFERROR(VLOOKUP(G22, Sheet2!$A:$B, 2, FALSE), A22) -> HKT Limited ( HKT Wireless Business ) | I22: AWS (Amazon Web Service) | M22: 463675202152 Root Login NA | S22: 44021 | T22: NA | U22: NA | Y22: Remark : No Order issue Customer Email : roger.kw.ng@pccw.com [9-Jul-2020] Added user to accoutns families ( group & user set up by Thomas )
A23: Completed | D23: Stanley Chan ( HKT ) | E23: 2883 2922 / 2883 2922 | G23: HKT Green Mini Bus | H23: =IFERROR(VLOOKUP(G23, Sheet2!$A:$B, 2, FALSE), A23) -> HKT Green Mini Bus | I23: AWS (Amazon Web Service) | K23: 955279921091 | L23: Csutomer email: sunnymak@firstbullion.com | M23: Root ID: hkt-gmb@hkt-cloud.com PW: hkt-gmbcus004 | Q23: 44116 | S23: 44113 | T23: CL544571 | U23: 658593/1-2 | V23: 102473 | Y23: Remark HKT owned account Contact Person : Stanley.yk.chan@pccw.com [8-Oct-20] HKT email account & AWS account created. [9-Oct-20] Sent request to ingram. Pending for ingram reply. [9-Oct-20] Stanley accept the invitation and welcome letter sent.Completed in CxS with completion date on 9-OCt-2020 [16-Oct-20] Cloudcheckr setup completed | Z23: N
A24: Cancelled | D24: Sunny Mak | E24: 21146105/ 92538264 | F24: Csutomer email: sunnymak@firstbullion.com | G24: FIRST ASIA MERCHANTS BULLION LIMITED | H24: =IFERROR(VLOOKUP(G24, Sheet2!$A:$B, 2, FALSE), A24) -> FIRST ASIA MERCHANTS BULLION LIMITED | I24: AWS (Amazon Web Service) | K24: 782264075267 | M24: Root Login : admin@goldwellcap.com | Q24: 43969 | T24: CL544184 | U24: 121718/1-2 | V24: 102375 | Y24: Csutomer email: sunnymak@firstbullion.com [14-May-2020] Pending for ingram reply email [15-May-2020] Invitation sent to customer. Pending for accept [20-Mar-2020] ASM reissue for 5 x separated orders [4-Jan-2020] cxl order
A25: Cancelled | D25: Sunny Mak | E25: 21146105/ 92538264 | G25: FIRST ASIA MERCHANTS BULLION LIMITED | H25: =IFERROR(VLOOKUP(G25, Sheet2!$A:$B, 2, FALSE), A25) -> FIRST ASIA MERCHANTS BULLION LIMITED | I25: AWS (Amazon Web Service) | K25: 477519521139 | M25: Root Login : admin@firstfx.bz | Q25: 43969 | T25: CL545380 | U25: 121718/3-4 | V25: 102386 | Y25: [15-May-2020] Invitation sent to customer. Pending for accept [4-Jan-2020] cxl order
A26: Cancelled | D26: Sunny Mak | E26: 21146105/ 92538264 | G26: FIRST ASIA MERCHANTS BULLION LIMITED | H26: =IFERROR(VLOOKUP(G26, Sheet2!$A:$B, 2, FALSE), A26) -> FIRST ASIA MERCHANTS BULLION LIMITED | I26: AWS (Amazon Web Service) | K26: 721697153034 | M26: Root Login : admin1@firstbullion.com | Q26: 43969 | T26: CL545401 | U26: 121718/5-6 | V26: 102385 | Y26: [15-May-2020] Invitation sent to customer. Pending for accept [4-Jan-2020] cxl order
A27: Cancelled | D27: Sunny Mak | E27: 21146105/ 92538264 | G27: FIRST ASIA MERCHANTS BULLION LIMITED | H27: =IFERROR(VLOOKUP(G27, Sheet2!$A:$B, 2, FALSE), A27) -> FIRST ASIA MERCHANTS BULLION LIMITED | I27: AWS (Amazon Web Service) | K27: 403046075669 | M27: Root Login : admin1@goldenfxlink.com | Q27: 43969 | T27: CL545407 | U27: 121718/7-8 | V27: 102384 | Y27: [15-May-2020] Invitation sent to customer. Pending for accept [4-Jan-2020] cxl order
A28: Cancelled | D28: Sunny Mak | E28: 21146105/ 92538264 | G28: FIRST ASIA MERCHANTS BULLION LIMITED | H28: =IFERROR(VLOOKUP(G28, Sheet2!$A:$B, 2, FALSE), A28) -> FIRST ASIA MERCHANTS BULLION LIMITED | I28: AWS (Amazon Web Service) | K28: 613594070113 | M28: Root Login : admin@goldenfxvip.com | Q28: 43969 | T28: CL545411 | U28: 121718/9-10 | V28: 102383 | Y28: [15-May-2020] Invitation sent to customer. Pending for accept [4-Jan-2020] cxl order
A29: Completed | D29: HENRY IP | E29: 68226722 | G29: EMPERIO GOLD AND SILVER COINS (HK) LTD | H29: =IFERROR(VLOOKUP(G29, Sheet2!$A:$B, 2, FALSE), A29) -> EMPERIO GOLD AND SILVER COINS (HK) LTD | I29: AWS (Amazon Web Service) | K29: 641582690281 | M29: Root Login: it@emperio-group.com | Q29: 44097 | S29: 44091 | T29: CL548980 | U29: 318774/1-2 | V29: 102458 | Y29: EMAIL : HENRYIP@EMPERIO-GROUP.COM [16-Sep-2020] Submitted request to Ingram [17-Sep-2020] Cus accepted the request. Completed in CxS. Pending usage consumption for cloudcheckr setup [18-Jan-2021] Welcome letter sent | Z29: N
A30: Completed | D30: Andy Ho | E30: 96121651 | G30: ULTRON TECHNOLOGY SG PTE. LIMITED (Pervious Name : EASY GREAT TECHNOLOGY LIMITED) | H30: =IFERROR(VLOOKUP(G30, Sheet2!$A:$B, 2, FALSE), A30) -> ULTRON TECHNOLOGY SG PTE. LIMITED | I30: Alibaba Cloud | K30: 5835359715465752 | M30: Alibaba Admin : dns.admin@ecg-tech.com Company Name chang to "ULTRON TECHNOLOGY SG PTE. LIMITED" | P30: Alibaba Cloud Admin Login Email: 5129223590947611 (hostmaster@naverhk.com ) | Q30: 43959 | S30: 43964 | T30: CL542163 | U30: 081569/1-2 | V30: 102364 | Y30: Alibaba Cloud Account ID : 5835359715465752 (dns.admin@ecg-tech.com ) Alibaba Cloud Admin Login Email: 5129223590947611 (hostmaster@naverhk.com ) [11-May-2020] Pending for Alibaba to proceed. Takes 1-2 days [13-May-2020] Completed on 13-May-2020. [18-May-2020] Completed in CxS with completion date on 13-May. [28-Apr-2021] Migration request from Zens to B-Data by Thomas [2-Jun-2021] Migration done on 2-Jun forUID. 5835359715465752 (dns.admin@ecg-tech.com )
A31: Cancelled | D31: Andy Ho | E31: 96121651 | F31: customer email: andy.ho@ecg-tech.com | G31: ULTRON TECHNOLOGY SG PTE. LIMITED (Pervious Name : EASY GREAT TECHNOLOGY LIMITED) | H31: =IFERROR(VLOOKUP(G31, Sheet2!$A:$B, 2, FALSE), A31) -> ULTRON TECHNOLOGY SG PTE. LIMITED | I31: AWS (Amazon Web Service) | K31: 787762068875 | M31: Root Login : sysadmin@889bcd.com | Q31: 43958 | T31: CL543185 | U31: 684634/1-2 | V31: 102366 | Y31: customer email: andy.ho@ecg-tech.com Will proceed another acc first [28-Jan-2021] sent email to salesruby for status update. [17-Feb-2021] Order cxl.
A32: Completed | D32: Andy Ho | E32: 96121651 | F32: customer email: andy.ho@ecg-tech.com | G32: ULTRON TECHNOLOGY SG PTE. LIMITED (Pervious Name : EASY GREAT TECHNOLOGY LIMITED) | H32: =IFERROR(VLOOKUP(G32, Sheet2!$A:$B, 2, FALSE), A32) -> ULTRON TECHNOLOGY SG PTE. LIMITED | I32: AWS (Amazon Web Service) | K32: 590419121026 | L32: Ilovecoin (Easy Great) | M32: Root Login : hostmaster@ilovecoin.com Company Name chang to "ULTRON TECHNOLOGY SG PTE. LIMITED" | Q32: 43972 | S32: 43969 | T32: CL544252 | U32: 475806/1-2 | V32: 102376 | Y32: customer email: andy.ho@ecg-tech.com [14-May-2020] Pending for ingram reply email [15-May-2020] Invitation sent to customer. Pending for accept [18-May-2020] Customer accepted and added customer to Cloud Checkr ilovecoin ( Easy Great). Completed in CxS. [8-Aug-2022] Sent request to martin to removed cus from HKT account. Done
A33: Completed | D33: Andy Ho | E33: 96121651 | G33: ULTRON TECHNOLOGY SG PTE. LIMITED (Pervious Name : EASY GREAT TECHNOLOGY LIMITED) | H33: =IFERROR(VLOOKUP(G33, Sheet2!$A:$B, 2, FALSE), A33) -> ULTRON TECHNOLOGY SG PTE. LIMITED | I33: Alibaba Cloud | K33: Alibaba Cloud Account ID : 5129223590947611 | M33: Alikbaba Admin : hostmaster@naverhk.com Company Name chang to "ULTRON TECHNOLOGY SG PTE. LIMITED" | Q33: 43972 | S33: 43970 | T33: CL544189 | U33: 057011/1-2 | V33: 102374 | Y33: Alibaba Cloud Account ID : 5129223590947611 [19-May-2020] Ann updated that Linked to HKT on 12-May (hostmaster@naverhk.com).Completed in CxS with completiondate on 19-May-2020 ( can't put remark )
A34: Completed | D34: Andy Ho | E34: 96121651 | F34: customer email: andy.ho@ecg-tech.com | G34: ULTRON TECHNOLOGY SG PTE. LIMITED (Pervious Name : EASY GREAT TECHNOLOGY LIMITED) | H34: =IFERROR(VLOOKUP(G34, Sheet2!$A:$B, 2, FALSE), A34) -> ULTRON TECHNOLOGY SG PTE. LIMITED | I34: AWS (Amazon Web Service) | K34: 484603839389 | L34: Hbeemail (Easy Great) | M34: Root Login : pmjp@hbeemail.com Company Name chang to "ULTRON TECHNOLOGY SG PTE. LIMITED" | Q34: 43972 | S34: 43971 | T34: CL544208 | U34: 42533/1-2 | V34: 102377 | Y34: customer email: andy.ho@ecg-tech.com [13-May] submitted to ingram. Pending for reply [15-May-2020] Invitation sent to customer. Pending for accept [20-May-2020] Add customer in Cloud Checkr Hbeemail (Easy Great). Completed in CxS. [8-Aug-2022] Sent request to martin to removed cus from HKT account. Done
A35: Completed | D35: Mr. Jacky Hui | E35: 96742005 | F35: Contact Person: jacky.hui@ddaapp.com | G35: DDAAPP Studio | H35: =IFERROR(VLOOKUP(G35, Sheet2!$A:$B, 2, FALSE), A35) -> DDAAPP LIMITED | I35: AWS (Amazon Web Service) | K35: 889849555457 | M35: Login account : enterprise@ddaapp.com Password : 1u3oc7fibx | P35: Root Login : enterprise@ddaapp.com | Q35: 43808 | S35: 43840 | T35: CL548273 | U35: 821828/1-2 | V35: 102250 | Y35: AWS Account ID: 889849555457 Root Login : enterprise@ddaapp.com Contact Person: jacky.hui@ddaapp.com [4-Jun-2020] moved to Ingram Micro on 1-Jun and added into HKT family on 4-Jun.
A36: Completed | D36: Daniel Yeung | E36: 31016889 / 98633579 | F36: Email : daniel.cw.yeung@cityline.com.hk | G36: CITYLINE (HONG KONG) LIMITED | H36: =IFERROR(VLOOKUP(G36, Sheet2!$A:$B, 2, FALSE), A36) -> CITYLINE (HONG KONG) LIMITED | I36: AWS (Amazon Web Service) | K36: 5943307259 | M36: Root Login : disney@cityline.com.hk | O36: Address: 23/F, Legend Tower, 7 Shing Yip Street, Kwung Tong | Q36: 44111 | S36: 44147 | T36: CL549093 | U36: 592730/1-2 | V36: 102468 | Y36: Address: 23/F, Legend Tower, 7 Shing Yip Street, Kwung Tong Email : daniel.cw.yeung@cityline.com.hk [5-Oct-2020] AWS root emil. Penidng for sales to provide [21-Oct-2020] AMSAMMI provbide root login of AWS ID: 697887384373. Pending for the 2nd root login. [6-Nov-2020] Submit the requets for 005943307259 first as per AM Sammi request and pending for ingram linkup. [10-Nov-2020] account linked. Pending for cus to accept invitation. [12-Nov-2020] AM Sammi updated that cus has accepted the invitation of AWS ID: 005943307259. Pendng for the 2nd root login for linkage [13-Nov-20] welcome letter sent ( AWS ID: 005943307259 ) [14-Jan-2020] The pending acc(AWS ID: 697887384373) will be split into another order. Completed (AWS ID: 005943307259) order in System [5-Jan-2023] Rec'd email from Product Thomas for the termination of this account. Remove rights in Cloud Checkr and Martin will unlink the account in AWS organization. Termination order will be issued later with SRD on 6-Feb-2023. [18-Dec-2023] Confirm by Katie Chai CL549093 is no more usage since 1 Mar 2023. Completed order in CxS | Z36: N
A37: Completed | D37: Jack Leung | E37: 2610 8769 / 96023323 | F37: Customer Email: jackleung@chowtaifook.com | G37: CHOW TAI FOOK JEWELLERY CO LTD | H37: =IFERROR(VLOOKUP(G37, Sheet2!$A:$B, 2, FALSE), A37) -> CHOW TAI FOOK JEWELLERY CO LTD | I37: AWS (Amazon Web Service) | J37: 726125834629 | K37: 275030332822 | M37: Root Login : aws@chowtaifook.com | Q37: 44034 | S37: 44034 | T37: CL557719 | U37: 578448/1-2 | V37: 102416 | Y37: Customer Email: jackleung@chowtaifook.com [22-Jul-20] Submitted request to Ingram. Customer accepted invitation [27-Jul-20] CloudCheckr setup completed. Welcome letter sent. Completed in Cxs with completion date on 22-Jul-2020. [18-Dec-2023] Confirm by Lok PS Job has done. Close CxS no.: 829459/1 | Z37: N | AA37: N
A38: Completed | D38: Jack Leung | E38: 2610 8769 / 96023323 | G38: CHOW TAI FOOK JEWELLERY CO LTD (vcchoi) | H38: =IFERROR(VLOOKUP(G38, Sheet2!$A:$B, 2, FALSE), A38) -> CHOW TAI FOOK JEWELLERY CO LTD | I38: AWS (Amazon Web Service) | J38: 726125834629 | K38: 757895108869 | M38: Root Login : vcchoi@chowtaifook.com | O38: Address: 25/F , World Peace centre, 41-55 Wo Tong Tsui St, Kwai Chung, NT | Q38: 44113 | S38: 44113 | T38: CL547335 | U38: 543588/1-2 | V38: 102470 | Y38: Remark: PS job ( pls pass to Johnny Team Address: 25/F , World Peace centre, 41-55 Wo Tong Tsui St, Kwai Chung, NT [6-Oct-2020] Pending for Cus to join. [9-Oct-2020] Ingram resent invitation as the invitation got some issue showing invitation cxl. [12-Oct-2020] Consultant Tony confirmed invitation accept done. Completed order in CxS with completion date on 9-Oct. Inform AM to issue PS job order. Pending for usage consumption for cloudchecr setup and PS job order [16-Oct-2020] Informed by Thomas that there are two PS job ( TM1 + Lamdba ).Thomas to clarify with ASM [29-Oct-2020] Setup CloudCheckr Acc and welcome letter sent [18-Dec-2023] Confirm by Lok PS Job has done. Completed order in CxS | Z38: N
A39: Completed | D39: Croven Phang | E39: 63365303 | F39: Customer Email: croven.phang@yahoo.com.sg | G39: Celestial Key Ventures Limited | H39: =IFERROR(VLOOKUP(G39, Sheet2!$A:$B, 2, FALSE), A39) -> Celestial Key Ventures Limited | I39: Microsoft Azure | M39: CSP Domain: ckvl.onmicrosoft.com | Q39: 43993 | S39: 43990 | T39: CL547398 | U39: RN498425/1-2 | V39: 102400 | Y39: Customer Email: croven.phang@yahoo.com.sg [9-Jun-2020] License has been assigned. Completed order in CxS with completion date on 8-Jun,
A40: Completed | D40: Roland Wong(GLP) | E40: +853 8982 0209/+853 6333 0729 | G40: CAM 8 PCCW (Macau) Ltd c/o SJM | H40: =IFERROR(VLOOKUP(G40, Sheet2!$A:$B, 2, FALSE), A40) -> CAM 8 PCCW (Macau) Ltd c/o SJM | I40: Alibaba Cloud | K40: Alibaba Cloud Account ID :5913782617694380 | M40: Alibaba Admin : itsoc@macausjm-glp.com | Q40: 43887 | S40: 43894 | T40: CL545947 | U40: 050255/1-2 | V40: 102330 | Y40: Alibaba Cloud Admin Login Email: itsoc@macausjm-glp.com [2-Mar-2020] Backdate order. Ann has provisioned the tenant to customer wit SRD on 26-Feb-2020. [4-Mar-2020] Order completed in CxS with completion date marked on 26-Feb-2020. [28-Apr-2021] Migration request from Zens to B-Data by Thomas
A41: Completed | D41: Dominie Liang Jason Ngan | E41: 66288524 6888 0042 | G41: Bindo Lab Limited | H41: =IFERROR(VLOOKUP(G41, Sheet2!$A:$B, 2, FALSE), A41) -> Bindo Lab Limited | I41: Google Cloud Platform (GCP) | Q41: 43738 | S41: 43756 | T41: CL547587 | U41: 304107/1-2 | V41: 102210 | Y41: backdate order. (SP handled by product team)
A42: Completed | D42: Ray Tang | E42: 28944010 / 96597430 | G42: AXA CHINA REGION INSURANCE CO LTD | H42: =IFERROR(VLOOKUP(G42, Sheet2!$A:$B, 2, FALSE), A42) -> AXA CHINA REGION INSURANCE CO LTD | I42: AWS (Amazon Web Service) | K42: 956093293977 | L42: AXA China Region Insurance Company Ltd | M42: axasahkt@hkt-cloud.com | Q42: 43936 | S42: 43930 | T42: CL541308 | U42: 499373/1-2 | V42: 102356 | Y42: [27-Apr-2020 ] Order completed in CxS with completion date marked on 9-Apr-2020. Account Provisioned by Thomas Remark: Company name in ASW HKT AXA speech Analytics
A43: Completed | D43: Tony Ng | E43: 2188 7269 | F43: tony.ng@hkairport.com | G43: AIRPORT AUTHORITY | H43: =IFERROR(VLOOKUP(G43, Sheet2!$A:$B, 2, FALSE), A43) -> AIRPORT AUTHORITY | I43: AWS (Amazon Web Service) | J43: 838776425275 | K43: 612931591519 | M43: Login account : hkairporthkt@hkt-cloud.com Password : iocigrxgl2 | Q43: 43891 | S43: 43889 | T43: CL552789 | U43: 195736/3-4 | V43: 102323 | Y43: This account is managed by HKT AWS ID: 612931591519 Root Email: hkairporthkt@hkt-cloud.com Contact Person: tony.ng@hkairport.com [2-Mar-2020] completed in CxS with completion date on 28-Feb-2020 [4-Jun-2020] moved to Ingram Micro on 1-Jun and added into HKT family on 4-Jun.
A44: Completed | D44: Tony Ng | E44: 2188 7269 | F44: tony.ng@hkairport.com | G44: AIRPORT AUTHORITY | H44: =IFERROR(VLOOKUP(G44, Sheet2!$A:$B, 2, FALSE), A44) -> AIRPORT AUTHORITY | I44: Microsoft Azure | Q44: 43891 | S44: 43891 | T44: CL552789 | U44: 195736/1-2 | V44: 102322 | Y44: Peter has provisioned account for customer. [2-Mar-2020] Completed in CxS qwith completion date on 1-Mar-2020 [4-Jun-2020] moved to Ingram Micro on 1-Jun and added into HKT family on 4-Jun.
A45: Completed | D45: Tony Ng | E45: 2188 7269 | F45: tony.ng@hkairport.com | G45: AIRPORT AUTHORITY | H45: =IFERROR(VLOOKUP(G45, Sheet2!$A:$B, 2, FALSE), A45) -> AIRPORT AUTHORITY | I45: Microsoft Azure | L45: rg-iot-zevent-sqcc-001 | Q45: 43901 | R45: 45385 | S45: 43901 | T45: CL552691 | U45: 699841/1-2 | V45: 102322 | W45: UB24-00000732\1(OM) | Y45: Remark: Update PSEF code only. Refer to 195736/1-2
A46: Completed | D46: Tony Ng | E46: 2188 7269 | F46: tony.ng@hkairport.com | G46: AIRPORT AUTHORITY | H46: =IFERROR(VLOOKUP(G46, Sheet2!$A:$B, 2, FALSE), A46) -> AIRPORT AUTHORITY | I46: AWS (Amazon Web Service) | J46: 838776425275 | Q46: 43901 | R46: 45385 | S46: 43901 | T46: CL552789 | U46: 699841/3-4 | V46: 102323 | W46: UB24-00000732\1(OM) | Y46: Remark: Update PSEF code only. Refer to 195736/3-4
A47: Completed | D47: Edicon Lai | E47: 21276339 / 96620694 | G47: AASTOCKS.COM LIMITED | H47: =IFERROR(VLOOKUP(G47, Sheet2!$A:$B, 2, FALSE), A47) -> AASTOCKS.COM LIMITED | I47: Huawei Cloud | Q47: 44117 | S47: 44116 | T47: CL543057 | U47: 556596/1-2 | V47: 102474 | Y47: Remark: Support service will be provided by HUAWEI directly. No provisioning action is reqruired. [12-Oct-2020] Completed order in CxS with completion date on 12-Oct & Service Given date on 13-Oct. | Z47: N
A48: Completed | G48: 8 Securities Ltd ( New company name SOFI SECURITIES LIMITED (SOFI SERVICES ( HONG KONG ) LTD)) | H48: =IFERROR(VLOOKUP(G48, Sheet2!$A:$B, 2, FALSE), A48) -> SOFI SECURITIES LIMITED (SOFI SERVICES ( HONG KONG ) LTD) | I48: Alibaba Cloud | M48: Alibaba UID : 5497093001888295 Email : techops@sofi.hk | Q48: 43678 | T48: CL555456 | U48: 768321/1-2 | V48: 102198 | Y48: Alibaba ( provisioned by Ann) [28-Apr-2021] Migration request from Zens to B-Data by Thomas [15-Jul-2021]Bdataupdated that migartion completed
A49: Completed | D49: Elaine Lee / Terence Wu (technical contact) | E49: 22320200 / 22320254 | G49: 2GOTRADE LIMITED | H49: =IFERROR(VLOOKUP(G49, Sheet2!$A:$B, 2, FALSE), A49) -> 2GOTRADE LIMITED | I49: Alibaba Cloud | K49: Alibaba Cloud Account ID : 5180116684041583 | M49: Alibaba Admin : infrastructure-hk@2gotrade.com | Q49: 44074 | S49: 44074 | T49: CL548133 | U49: 020523/1-2 | V49: 102436 | Y49: [10-Aug-20] Pending for Alibaba to Link the account. Not to close case until further notice [ 01-Sep-20] Ann updated that acc linking completed on 31-Aug-2020. Order team revised order SRD to 31-Aug-20. Completed in CxS. [28-Apr-2021] Migration request from Zens to B-Data by Thomas [17-Jul-2021] checked migration completed on 2-Jun-2021by B-Data [12-Aug-2022] Offset done. <SD11524767>
A50: Completed | D50: Ernest Tsien | G50: SHISEIDO HONG KONG LIMITED | H50: =IFERROR(VLOOKUP(G50, Sheet2!$A:$B, 2, FALSE), A50) -> SHISEIDO HONG KONG LIMITED | I50: Microsoft Azure | Q50: 44123 | S50: 44131 | T50: CL551180 | U50: 3478/1-2 | V50: 102478 | Y50: [16-Oct-2020] PS job order receive. Passed to Johnny's team [23-Oct-2020] Pending for signed UAT ( updated by Lok ) [6-Nov-2020] sent email to Lok for UAT status [9-Nov-2020] UAT received. Completed in SRS with completion date on 27-Oct-2020. | Z50: Y
A51: Completed | D51: Victor Liu | E51: 28624428 / 96211193 | G51: MITSUBISHI CORPORATION (HK) LTD | H51: =IFERROR(VLOOKUP(G51, Sheet2!$A:$B, 2, FALSE), A51) -> MITSUBISHI CORPORATION (HK) LTD | I51: AWS (Amazon Web Service) | K51: 244335467891 | M51: Root ID : ml.hkgit@mitsubishicorp.com | O51: Address: 15/F , Tower 1, Admiratly centre, 18 Harcout Road, Central & Western | Q51: 44131 | S51: 44127 | T51: CL548394 | U51: 555130/1-2 | V51: 102482 | Y51: Address: 15/F , Tower 1, Admiratly centre, 18 Harcout Road, Central & Western [22-Oct-2020] Submittd request to ingram. Pending ingram linking [23-Oct-2020] Cus accepted the request. Completed order in CxS with completion date on 23-Oct. Pending for consumption for billing portal set up [18-Jan-2021] Welcome letter sent | Z51: N
A52: Completed | D52: Jack Leung | E52: 2610 8769 / 96023323 | G52: CHOW TAI FOOK JEWELLERY CO LTD | H52: =IFERROR(VLOOKUP(G52, Sheet2!$A:$B, 2, FALSE), A52) -> CHOW TAI FOOK JEWELLERY CO LTD | I52: AWS (Amazon Web Service) | J52: 726125834629 | K52: 275030332822 | M52: TM1 deployment for AWS ID 275030332822 | Q52: 44134 | S52: 44448 | T52: CL557719 | U52: 635013/1-2 | V52: 102416 | Y52: Remark: PS job BILL $33,000 to CL557719 ( TM1 deployment for AWS ID 275030332822) [23-Oct-2020] Passed to suport team [29-Oct-2020] Lok updated that still under testing [12-Nov-2020] sent email for status update [19-Nov-2020] sent email for status update again [12-Jan-2021] Sent email to Lok for update [8-Sep-2021] Sent email to Lok for update [9-Sep-2021] UAT recieved ( signed on 28-Dec-2021 ).Completed order in CxS with SRD n 28-Dec-2020 Have to inform Thomas once complete in system for bill issue | Z52: Y | AA52: N
A53: Completed | D53: Jack Leung | E53: 2610 8769 / 96023323 | G53: CHOW TAI FOOK JEWELLERY CO LTD (vcchoi) | H53: =IFERROR(VLOOKUP(G53, Sheet2!$A:$B, 2, FALSE), A53) -> CHOW TAI FOOK JEWELLERY CO LTD | I53: AWS (Amazon Web Service) | J53: 726125834629 | K53: 757895108869 | M53: Lambda deployment for AWS ID 757895108869 | Q53: 44134 | S53: 44448 | T53: CL547335 | U53: 175112/1-2 | V53: 102407 | Y53: Remark: PS job BILL $7,900 to CL547335 (Lambda deployment for AWS ID 757895108869 ) [23-Oct-2020] Passed to suport team [29-Oct-2020] Lok updated that still under testing [12-Nov-2020] sent email for status update [19-Nov-2020] sent email for status update again [12-Jan-2021] Sent email to Lok for update [8-Sep-2021] Sent email to Lok for update [9-Sep-2021] UAT recieved ( signed on 28-Dec-2021 ). Complete order in CxS by helpdesk due to completion issue Have to inform Thomas once complete in system for bill issue | Z53: Y
A54: Completed | D54: Stanley Chan ( HKT ) | E54: 2883 2922 / 2883 2922 | F54: Stanley.yk.chan@pccw.com | G54: CAM 8 AWS account for Green Motor Bus (for customer production workload) | H54: =IFERROR(VLOOKUP(G54, Sheet2!$A:$B, 2, FALSE), A54) -> CAM 8 AWS account for Green Motor Bus (for customer production workload) | I54: AWS (Amazon Web Service) | K54: 097339626419 | L54: hkt-gmb-prod | M54: Root ID: hkt-gmb-prod@hkt-cloud.com PW: hkt-gmbcus005 acc name: hkt-gmb-prod | Q54: 44134 | S54: 44131 | T54: CL540227 | U54: 445071/1-2 | V54: 102484 | Y54: Remark HKT owned account Contact Person : Stanley.yk.chan@pccw.com [27-Oct-20] HKT email account & AWS account created. Sent requset to ingram. Pending for ingram reply. [27-Oct-20] Stanley accepted the invitation. Completed order in CxS. [12-Nov-20] Cloudcheckr set completed. Add under existing account. welcome letter sent | Z54: N
A55: Completed | D55: Mark Mak | E55: 2883 4776 / 5188 0210 | G55: HKT Cloud EMS | H55: =IFERROR(VLOOKUP(G55, Sheet2!$A:$B, 2, FALSE), A55) -> HKT Cloud EMS | I55: AWS (Amazon Web Service) | K55: 346203265065 | M55: Root ID: hktcloudems@pccw.com | Q55: 44134 | S55: 44134 | T55: CL542767 | U55: 711144/1-2 | V55: 102486 | Y55: For internal use [28-Oct-20] Submit request to ingram. KC accepted the invitation. Pending for usage to set up billing and welcome letter [29-Oct-20] Pending for order to reflect in CxS [30-Oct-20] Completed order in CxS with completion date on 30-Oct-20 [3-Nov-202] Billing portal setup and welcome letter sent | Z55: N
A56: Completed | D56: Mark Mak | E56: 2883 4776 / 5188 0210 | G56: HKT Cloud EMS | H56: =IFERROR(VLOOKUP(G56, Sheet2!$A:$B, 2, FALSE), A56) -> HKT Cloud EMS | I56: Microsoft Azure | Q56: 44134 | S56: 44133 | T56: Pending | U56: Pending | V56: Pending | Y56: [29-Oct-2020] Acc provisioned. Pending for order no to complete case in CxS [27-Jul-2021] Acc for internal use only. No order issue. Case closed | Z56: N
A57: Completed | D57: Edicon Lai | E57: 21276339 / 96620694 | G57: AASTOCKS.COM LIMITED | H57: =IFERROR(VLOOKUP(G57, Sheet2!$A:$B, 2, FALSE), A57) -> AASTOCKS.COM LIMITED | I57: Huawei Cloud | Q57: 44148 | S57: 44116 | T57: CL548119 | U57: 462730/1-2 | V57: 102494 | Y57: Remark: Support service will be provided by HUAWEI directly. No provisioning action is reqruired. [12-Nov-2020] Completed order in CxS with completion date on 12-Nov & Service Given date on 13-Nov. | Z57: N
A58: Completed | D58: Edmond Chan | E58: 2883 6771 / 9760 3118 | F58: Email : edmond.mc.chan@pccw.com | G58: CCC CP29 | H58: =IFERROR(VLOOKUP(G58, Sheet2!$A:$B, 2, FALSE), A58) -> CCC CP29 | I58: Microsoft Azure | M58: Tenant ID : hktngsoc.onmicrosoft.com | Q58: 44158 | S58: 44152 | T58: CL540645 | U58: 770405/1-2 | V58: 1022498 | Y58: Email : edmond.mc.chan@pccw.com [17-Nov-20] Setup completed. Completed order in SRS. | Z58: N
A59: Completed | D59: Jason Yeung | E59: 21692109 | F59: Email: jyeung@incomepartners.com | G59: INCOME PARTNERS ASSET MANAGEMENT(HK)LTD | H59: =IFERROR(VLOOKUP(G59, Sheet2!$A:$B, 2, FALSE), A59) -> INCOME PARTNERS ASSET MANAGEMENT(HK)LTD | I59: AWS (Amazon Web Service) | K59: 570499519381 | M59: Root ID: aws_admin@incomepartners.com | O59: Address: Flat 3-4, 35/F, Cmabridge Hse, Taikoo Place, 979 Kings Road, Quarry Bay, HK | Q59: 44154 | S59: 44152 | T59: CL545786 | U59: 840622/1-2 | V59: 102500 | Y59: Email: jyeung@incomepartners.com Address: Flat 3-4, 35/F, Cmabridge Hse, Taikoo Place, 979 Kings Road, Quarry Bay, HK [17-Nov-20] Request sent to ingram and invitation sent Cus accepted & completed order in SRS. Pending for usage for billing portal setup and welcome letter. [20-Apr-2021] Checked usage on 17-Apr-2021. Welcome letter sent. | Z59: N
A60: Completed | D60: IT Suppport | E60: 23711810 | F60: email : itsupport@lawsgroup.com; 'Calvin Yeung' <calvin.yeung@lawsgroup.com> | G60: LAWS FASHION GROUP LIMITED | H60: =IFERROR(VLOOKUP(G60, Sheet2!$A:$B, 2, FALSE), A60) -> LAWS FASHION GROUP LIMITED | I60: AWS (Amazon Web Service) | K60: 10068276052 | M60: Root Login: aws@lawsgroup.com | O60: Address: Laws Commercial Plaza, 788 Cheung Sha Wan Road, KLN | Q60: 44165 | S60: 44165 | T60: CL552333 | U60: RN606144/1-2 | V60: 102502 | Y60: Address: Laws Commercial Plaza, 788 Cheung Sha Wan Road, KLN email : itsupport@lawsgroup.com; 'Calvin Yeung' <calvin.yeung@lawsgroup.com> [20-Nov-2020] Submit request to ingram nad ingram sent out invitation. Pending for cus accept. [24-Nov-2020] email to cus for status update [30-Nov-2020] Cus accepted the invitation. Completed in CxS. Pending for usage for welcome letter [4-Dec-2020] CloudCheckr acc setup and welcome letter sent. | Z60: N
A61: Pending | D61: Ben Yip | E61: 23026155 / 63439119 | F61: Email : ben.yip@modernbeautysalon.com | G61: MODERN BEAUTY SALON (HK) LTD | H61: =IFERROR(VLOOKUP(G61, Sheet2!$A:$B, 2, FALSE), A61) -> MODERN BEAUTY SALON (HK) LTD | I61: AWS (Amazon Web Service) | K61: 240396774091 | M61: Root Login:ben.yip@modernbeautysalon.com | O61: Address: Flat 6, Sino Industrial Plaza, 9 Kai Cheung Road, Kowloom Bay | Q61: 44161 | S61: 44159 | T61: CL552511 | U61: 580635/1-2 | V61: 102506 | Y61: Address: Flat 6, Sino Industrial Plaza, 9 Kai Cheung Road, Kowloom Bay Email : ben.yip@modernbeautysalon.com [24-Nov-2020] Request sent and cus accept. Completed order in CxS with service given date on 24-Nov-20. Pending for usage for cloudcheckr setup | Z61: N
A62: Completed | D62: Edicon Lai | E62: 21276339 / 96620694 | G62: AASTOCKS.COM LIMITED | H62: =IFERROR(VLOOKUP(G62, Sheet2!$A:$B, 2, FALSE), A62) -> AASTOCKS.COM LIMITED | I62: Huawei Cloud | Q62: 44161 | S62: 44159 | T62: CL552452 | U62: 801423/1-2 | V62: 102507 | Y62: Remark: Support service will be provided by HUAWEI directly. No provisioning action is reqruired. Project 3, separate invoice, create new NF number [24-Nov-2020] Completed order in CxS with completion date on 24-Nov & Service Given date on 26-Nov. | Z62: N
A63: Completed | D63: Jack Leung | E63: 2610 8769 / 96023323 | G63: CHOW TAI FOOK JEWELLERY CO LTD | H63: =IFERROR(VLOOKUP(G63, Sheet2!$A:$B, 2, FALSE), A63) -> CHOW TAI FOOK JEWELLERY CO LTD | I63: AWS (Amazon Web Service) | J63: 726125834629 | K63: 275030332822 | M63: Lift & Shift Migartion project (275030332822) | Q63: 44188 | S63: 44771 | T63: CL545015 | U63: 328227/1-2 | V63: 102516 | Y63: Remark: PS job ($450,000 )for 275030332822 (backdate order refer to main order CL557719 ) [18-Dec-2020] Passed to suport team [8-Sep-2021] Sent email to Lok for update [22-Sep-2022] Informed by Connie (Phase I Lift & Shift migration completed. Have informed Thomas to bill on this PS @Jul 29 2022 ) . Completed order in CxS with completion date on 29-Jul-2022. no UAT just email confirmed by Connie. Have to inform Thomas once complete in system for bill issue | Z63: Y | AA63: T3
A64: Completed | D64: Tony Chan | E64: 6033 4200 | G64: JARDINE MATHESON LTD | H64: =IFERROR(VLOOKUP(G64, Sheet2!$A:$B, 2, FALSE), A64) -> JARDINE MATHESON LIMITED | I64: Microsoft Azure | M64: Acc: JARDINEMATHESON.onmicrosoft.com. | Q64: 44196 | S64: 44210 | T64: CL545943 | U64: 571314 /1-2 | V64: 102518 | Y64: Contact Point : Tony Chan (tony.ck.chan@pccw.com) [18-Dec-2020] Pending for Tony reply domain name [21-Dec-2020] Revised SRD from 22-Dec-2020 to 31-Dec-2020 [30-Dec-2020] Revised SRD from 31-Dec-2020 to 14-Jan-2020 [12-Jan-2021] Sent email to Tony for update of domain name. confirmed domain. Tenant ready and send welcome letter on SRD only [15-Jan-2021] welcome letter sent and completed order in CxS | Z64: N
A65: Completed | D65: Sunny Mak / Jerry Leung | E65: 21146105/ 92538264 2114 6104 / 60236827 | F65: Contact emauil : admin1@firstbullion.com | G65: FIRST ASIA MERCHANTS BULLION LIMITED | H65: =IFERROR(VLOOKUP(G65, Sheet2!$A:$B, 2, FALSE), A65) -> FIRST ASIA MERCHANTS BULLION LIMITED | I65: AWS (Amazon Web Service) | K65: 7869699217617 | M65: Root Login : registration@365online.bz | O65: Address: 6/F, Allied Kajima Building, 134 -143 Gloucester Road, Wan Chai, Hong Kong | Q65: 44194 | S65: 44195 | T65: CL542979 | U65: 532189/1-2 | V65: 102526 | Y65: Contact emauil : admin1@firstbullion.com Address: 6/F, Allied Kajima Building, 134 -143 Gloucester Road, Wan Chai, Hong Kong [29-Dec-2020] Duplicate acc with previous order . Checking with Thomas & AM [30-Dec-2020] Submitted request for 2x new AWS ID and reuqest to resend invitation link for the other 4 x AWS ID [31-Dec-2020] AMStephen said cus has accepted the invitation on 30-Dec-2020. Completed order in CxS. [6-Jan-2020] Order issued. Welcome letter sent. | Z65: N
A66: Completed | D66: Mr. Jacky Hui | E66: 96742005 | G66: DDAAPP LIMITED | H66: =IFERROR(VLOOKUP(G66, Sheet2!$A:$B, 2, FALSE), A66) -> DDAAPP LIMITED | I66: AWS (Amazon Web Service) | K66: 024407781088 | M66: Root Login : CFD_CI@hanglung.com | Q66: 44202 | S66: 44201 | T66: CL548769 | U66: 62914 /1-2 | V66: 102528 | Y66: Address: Workshop G, 17/F, , Century Industrial Centre, 33-35 Au Pui Wan Street, Shatin [4-Jan-2021] submitted request to ingram, pending for cus to accept [5-Jan-2021] Cus accepted invitation. Completed order in CxS. Pending for usage to send out welcome letter [18-Jan-2021] Welcome letter sent | Z66: N
A67: Completed | D67: Sunny Mak / Jerry Leung | E67: 21146105/ 92538264 2114 6104 / 60236827 | F67: Contact emauil : admin1@firstbullion.com | G67: FIRST ASIA MERCHANTS BULLION LIMITED | H67: =IFERROR(VLOOKUP(G67, Sheet2!$A:$B, 2, FALSE), A67) -> FIRST ASIA MERCHANTS BULLION LIMITED | I67: AWS (Amazon Web Service) | K67: 169734347621 | M67: Root Login : admin@amercantile.com | O67: Address: 6/F, Allied Kajima Building, 134 -143 Gloucester Road, Wan Chai, Hong Kong | Q67: 44194 | S67: 44195 | T67: CL549414 | U67: 683641/1-2 | V67: 102531 | Y67: Contact emauil : admin1@firstbullion.com Address: 6/F, Allied Kajima Building, 134 -143 Gloucester Road, Wan Chai, Hong Kong [29-Dec-2020] Duplicate acc with previous order . Checking with Thomas & AM [30-Dec-2020] Submitted request for 2x new AWS ID and reuqest to resend invitation link for the other 4 x AWS ID [31-Dec-2020] AMStephen said cus has accepted the invitation on 30-Dec-2020. Completed order in CxS. [6-Jan-2020] Order issued. Welcome letter sent. Completed order in CxS | Z67: N
A68: Completed | D68: Sunny Mak / Jerry Leung | E68: 21146105/ 92538264 2114 6104 / 60236827 | F68: Contact emauil : admin1@firstbullion.com | G68: FIRST ASIA MERCHANTS BULLION LIMITED | H68: =IFERROR(VLOOKUP(G68, Sheet2!$A:$B, 2, FALSE), A68) -> FIRST ASIA MERCHANTS BULLION LIMITED | I68: AWS (Amazon Web Service) | K68: 477519521139 | M68: oot Login : admin@firstfx.bz | O68: Address: 6/F, Allied Kajima Building, 134 -143 Gloucester Road, Wan Chai, Hong Kong | Q68: 44194 | S68: 44195 | T68: CL549458 | U68: 683641/3-4 | V68: 102530 | Y68: Contact emauil : admin1@firstbullion.com Address: 6/F, Allied Kajima Building, 134 -143 Gloucester Road, Wan Chai, Hong Kong [29-Dec-2020] Duplicate acc with previous order . Checking with Thomas & AM [30-Dec-2020] Submitted request for 2x new AWS ID and reuqest to resend invitation link for the other 4 x AWS ID [31-Dec-2020] AMStephen said cus has accepted the invitation on 30-Dec-2020. Completed order in CxS. [6-Jan-2020] Order issued. Welcome letter sent. Completed order in CxS | Z68: N
A69: Completed | D69: Sunny Mak / Jerry Leung | E69: 21146105/ 92538264 2114 6104 / 60236827 | F69: Contact emauil : admin1@firstbullion.com | G69: FIRST ASIA MERCHANTS BULLION LIMITED | H69: =IFERROR(VLOOKUP(G69, Sheet2!$A:$B, 2, FALSE), A69) -> FIRST ASIA MERCHANTS BULLION LIMITED | I69: AWS (Amazon Web Service) | K69: 721697153034 | M69: Root Login : admin1@firstbullion.com | O69: Address: 6/F, Allied Kajima Building, 134 -143 Gloucester Road, Wan Chai, Hong Kong | Q69: 44194 | S69: 44195 | T69: CL549474 | U69: 683641/5-6 | V69: 102536 | Y69: Contact emauil : admin1@firstbullion.com Address: 6/F, Allied Kajima Building, 134 -143 Gloucester Road, Wan Chai, Hong Kong [29-Dec-2020] Duplicate acc with previous order . Checking with Thomas & AM [30-Dec-2020] Submitted request for 2x new AWS ID and reuqest to resend invitation link for the other 4 x AWS ID [31-Dec-2020] AMStephen said cus has accepted the invitation on 30-Dec-2020. Completed order in CxS. [6-Jan-2020] Order issued. Welcome letter sent. Completed order in CxS | Z69: N
A70: Completed | D70: Sunny Mak / Jerry Leung | E70: 21146105/ 92538264 2114 6104 / 60236827 | F70: Contact emauil : admin1@firstbullion.com | G70: FIRST ASIA MERCHANTS BULLION LIMITED | H70: =IFERROR(VLOOKUP(G70, Sheet2!$A:$B, 2, FALSE), A70) -> FIRST ASIA MERCHANTS BULLION LIMITED | I70: AWS (Amazon Web Service) | K70: 403046075669 | M70: Root Login : admin1@goldenfxlink.com | O70: Address: 6/F, Allied Kajima Building, 134 -143 Gloucester Road, Wan Chai, Hong Kong | Q70: 44194 | S70: 44195 | T70: CL549630 | U70: 683641/7-8 | V70: 102535 | Y70: Contact emauil : admin1@firstbullion.com Address: 6/F, Allied Kajima Building, 134 -143 Gloucester Road, Wan Chai, Hong Kong [29-Dec-2020] Duplicate acc with previous order . Checking with Thomas & AM [30-Dec-2020] Submitted request for 2x new AWS ID and reuqest to resend invitation link for the other 4 x AWS ID [31-Dec-2020] AMStephen said cus has accepted the invitation on 30-Dec-2020. Completed order in CxS. [6-Jan-2020] Order issued. Welcome letter sent. Completed order in CxS | Z70: N
A71: Completed | D71: Sunny Mak / Jerry Leung | E71: 21146105/ 92538264 2114 6104 / 60236827 | F71: Contact emauil : admin1@firstbullion.com | G71: FIRST ASIA MERCHANTS BULLION LIMITED | H71: =IFERROR(VLOOKUP(G71, Sheet2!$A:$B, 2, FALSE), A71) -> FIRST ASIA MERCHANTS BULLION LIMITED | I71: AWS (Amazon Web Service) | K71: 613594070113 | M71: Root Login : admin@goldenfxvip.com | O71: Address: 6/F, Allied Kajima Building, 134 -143 Gloucester Road, Wan Chai, Hong Kong | Q71: 44194 | S71: 44195 | T71: CL549902 | U71: 683641/9-10 | V71: 102534 | Y71: Contact emauil : admin1@firstbullion.com Address: 6/F, Allied Kajima Building, 134 -143 Gloucester Road, Wan Chai, Hong Kong [29-Dec-2020] Duplicate acc with previous order . Checking with Thomas & AM [30-Dec-2020] Submitted request for 2x new AWS ID and reuqest to resend invitation link for the other 4 x AWS ID [31-Dec-2020] AMStephen said cus has accepted the invitation on 30-Dec-2020. Completed order in CxS. [6-Jan-2020] Order issued. Welcome letter sent. Completed order in CxS | Z71: N
A72: Completed | D72: Mr. Jacky Hui | E72: 96742005 | G72: DDAAPP LIMITED | H72: =IFERROR(VLOOKUP(G72, Sheet2!$A:$B, 2, FALSE), A72) -> DDAAPP LIMITED | I72: AWS (Amazon Web Service) | Q72: 44209 | S72: 44300 | T72: CL548769 | U72: 602640 /1-2 | V72: 102528 | Y72: Remark: PS job only (public cloud configuration $ 33,480) + T2 support [14-Jan-2020] Passed PS job order to PS team. Pending for job completion by PS team [27-Jan-2-21] Passed PS job to T2 Cloud support team as well ( NPO ) . Have to inform Thomas once complete in system for bill issue [14-Apr-2021] UAT rec'd with signed on 12-Apr-2021. Completed order in CxS with completion date on 12-Apr-21. | Z72: Y
A73: Completed | D73: Ron Ko | E73: 23038766 | G73: WING FUNG CREDIT LIMITED | H73: =IFERROR(VLOOKUP(G73, Sheet2!$A:$B, 2, FALSE), A73) -> WING FUNG CREDIT LIMITED | I73: AWS (Amazon Web Service) | K73: 817924706531 | L73: WF_CRE001 | M73: Login account : credit_infra@wfgold.com (billing acc : infrastructure@wfgold.com) | Q73: 44216 | S73: 44223 | T73: CL545590 | U73: 253743./1-2 | V73: 102542 | Y73: Customer Email: ronko@wfgold.com Address: 20/F, Wing On House, 71 Des Voeux Road C, Central [26-Jan-21] Submitted request to Ingram. [27-Jan-21] Cs accepted the invitation. Completion in CxS. Pending for usage for welcome letter [1-Feb-21] Billing acc added . welcom letter sent | Z73: N
A74: Completed | D74: Kenneth Wong | E74: 31206263 | F74: Email : kennethwong@hksi.org | G74: HONG KONG SECURITIES AND INV INSTITUTE | H74: =IFERROR(VLOOKUP(G74, Sheet2!$A:$B, 2, FALSE), A74) -> HONG KONG SECURITIES AND INV INSTITUTE | I74: AWS (Amazon Web Service) | K74: 644017739101 | L74: HKSI | M74: Root Login : it@hksi.org | O74: Address: Flat 510, 5/F, Wing On Centre, 111 Connaught Road Central , Sheung Wan | Q74: 44226 | S74: 44252 | T74: CL554283 | U74: 570858/1-6 | V74: 102548 | Y74: Address: Flat 510, 5/F, Wing On Centre, 111 Connaught Road Central , Sheung Wan Email : kennethwong@hksi.org [29-Jan-2021] sent request to ingram. Pending for cus accept [1-Feb-2021] Cus got issue in joining to HKT. Cus has to contact previous org to disconnect for them. Pending cus reply [2-Feb-2021] email to cus for update ( welcome letter with 3 x AWS acc ready in draft ) [24-Feb] Cus request resend invitation [25-Feb-2021] AMHong replied cus accepted invitation. Completed order in CxS. welcome letter sent. Pending for usage to add acc in portal [1-Mar-2021] Account added. Case Closed | Z74: N
A75: Completed | D75: Kenneth Wong | E75: 31206263 | F75: Email : kennethwong@hksi.org | G75: HONG KONG SECURITIES AND INV INSTITUTE | H75: =IFERROR(VLOOKUP(G75, Sheet2!$A:$B, 2, FALSE), A75) -> HONG KONG SECURITIES AND INV INSTITUTE | I75: AWS (Amazon Web Service) | K75: 701425533496 | L75: IT-UAT1 | M75: Root Login: it-uat1@hksi.org | O75: Address: Flat 510, 5/F, Wing On Centre, 111 Connaught Road Central , Sheung Wan | Q75: 44226 | S75: 44225 | T75: CL554291 | U75: 570858/1-6 | V75: 102547 | Y75: Address: Flat 510, 5/F, Wing On Centre, 111 Connaught Road Central , Sheung Wan Email : kennethwong@hksi.org [29-Jan-2021] sent request to ingram. Cus accept invitation. [1-Feb-2021] Completed in CxS with completion date on 29-Jan-2021. Pending for the reamining acc to send welcome letter ( group acc create and pending for user acc ) [25-Feb-2021] welcome letter sent | Z75: N
A76: Completed | D76: Kenneth Wong | E76: 31206263 | G76: HONG KONG SECURITIES AND INV INSTITUTE | H76: =IFERROR(VLOOKUP(G76, Sheet2!$A:$B, 2, FALSE), A76) -> HONG KONG SECURITIES AND INV INSTITUTE | I76: AWS (Amazon Web Service) | K76: 599186243446 | L76: HKSI Production1 | M76: Root Login : it-prod1@hksi.org | Q76: 44226 | S76: 44225 | T76: CL554297 | U76: 570858/1-6 | V76: 102546 | Y76: Address: Flat 510, 5/F, Wing On Centre, 111 Connaught Road Central , Sheung Wan Email : kennethwong@hksi.org [29-Jan-2021] sent request to ingram. Cus accept invitation. [1-Feb-2021] Completed in CxS with completion date on 29-Jan-2021. Pending for the reamining acc to send welcome letter ( group acc create and pending for user acc ) [25-Feb-2021] welcome letter sent | Z76: N
A77: Completed | D77: Ron Ko | E77: 23038766 | F77: Customer Email: ronko@wfgold.com | G77: WING FUNG SECURITIES LIMITED | H77: =IFERROR(VLOOKUP(G77, Sheet2!$A:$B, 2, FALSE), A77) -> WING FUNG SECURITIES LIMITED | I77: AWS (Amazon Web Service) | K77: 770974816075 | L77: WF_SEC001 | M77: Root Login: sec_infra@wfgold.com | O77: Address: 20/F, Wing On House, 71 Des Voeux Road C, Central | Q77: 44236 | S77: 44231 | T77: CL548143 | U77: 498026/1-2 | V77: 102550 | Y77: Customer Email: ronko@wfgold.com Address: 20/F, Wing On House, 71 Des Voeux Road C, Central [3-Feb-21] Submitted request to Ingram. [4-Feb-21] Cus accepted. Completed order in CxS. Pending for usgage for billing acc setup and welcome letter [9-Feb-21] Welcome letter sent. | Z77: N
A78: Completed | D78: Tony Chan | E78: 6033 4200 | G78: JARDINE MATHESON LTD | H78: =IFERROR(VLOOKUP(G78, Sheet2!$A:$B, 2, FALSE), A78) -> JARDINE MATHESON LIMITED | I78: Microsoft Azure | Q78: 44222 | S78: 44222 | T78: CL545943 | U78: 465335/1-2 | V78: 102518 | Y78: Remark: PS job order of 571314 /1-2 ( configuration charge $139253) [16-Feb-2021] Passed order to Johnny's team. Completed order in system with SRD on 26-Jan-2021 by ASM Kelvin Yip requet. | Z78: Y
A79: Completed | D79: Kenneth Wong | E79: 31206263 | F79: Email : kennethwong@hksi.org | G79: HONG KONG SECURITIES AND INV INSTITUTE | H79: =IFERROR(VLOOKUP(G79, Sheet2!$A:$B, 2, FALSE), A79) -> HONG KONG SECURITIES AND INV INSTITUTE | I79: AWS (Amazon Web Service) | K79: 741606553494 | L79: HKSI ITDEV | M79: Root Login : it-dev1@hksi.org | O79: Address: Flat 510, 5/F, Wing On Centre, 111 Connaught Road Central , Sheung Wan | Q79: 44252 | S79: 44251 | T79: CL543498 | U79: rn889504/1-2 | V79: 102557 | Y79: Address: Flat 510, 5/F, Wing On Centre, 111 Connaught Road Central , Sheung Wan Email : kennethwong@hksi.org [18-Feb-2021] Fail to submit request to ingram. Pending for ingram reply [24-Feb-2021] Request to amend AWS ID. [25-Feb-2021] Completed order in CxS. welcome letter sent. Pending for usage to add acc in portal [1-Mar-2021] Account added. Case closed | Z79: N
A80: Completed | D80: Kenneth Wong | E80: 31206263 | F80: Email : kennethwong@hksi.org | G80: HONG KONG SECURITIES AND INV INSTITUTE | H80: =IFERROR(VLOOKUP(G80, Sheet2!$A:$B, 2, FALSE), A80) -> HONG KONG SECURITIES AND INV INSTITUTE | I80: AWS (Amazon Web Service) | K80: 513913584737 | L80: HKSI-WAM2021 | M80: Root Login : it-prodwam@hksi.org | O80: Address: Flat 510, 5/F, Wing On Centre, 111 Connaught Road Central , Sheung Wan | Q80: 44252 | S80: 44252 | T80: CL543918 | U80: rn889504/3-4 | V80: 102556 | Y80: Address: Flat 510, 5/F, Wing On Centre, 111 Connaught Road Central , Sheung Wan Email : kennethwong@hksi.org [18-Feb-2021] Fail to submit request to ingram. Pending for ingram reply [24-Feb-2021] Request to amend AWS ID. [25-Feb-2021] Completed order in CxS. welcome letter sent. Pending for usage to add acc in portal [1-Mar-2021] Account added. Case closed | Z80: N
A81: Processing | D81: Tony Chan | E81: 6033 4200 | G81: JARDINE MATHESON LTD | H81: =IFERROR(VLOOKUP(G81, Sheet2!$A:$B, 2, FALSE), A81) -> JARDINE MATHESON LIMITED | I81: Microsoft Azure | Q81: 44237 | T81: CL545943 | U81: 272113/1-2 | V81: 102518 | Y81: Remark: PS job order of 571314 /1-2 ( configuration charge $ 65330 )Enable Sentinal on Azure [3-Mar-2021] Passed order to Johnny's team. [9-Sep-2021] Sent to Lok for status update | Z81: Y | AA81: N
A82: Completed | D82: Rex Chan | E82: - | G82: GRAND STRONG HOLDINGS LIMITED | H82: =IFERROR(VLOOKUP(G82, Sheet2!$A:$B, 2, FALSE), A82) -> GRAND STRONG HOLDINGS LIMITED | I82: Microsoft Azure | Q82: 44043 | T82: CL543818 | U82: 527617/1-2 | Y82: Termination order [11-Mar-2021] Prodcut Peter confirmed that no action to be taken for this termination order. No need to delete | Z82: N
A83: Completed | D83: Davidson Yau | E83: 25837747 / 61558555 | G83: GAW CAPITAL ADVISORS LIMITED | H83: =IFERROR(VLOOKUP(G83, Sheet2!$A:$B, 2, FALSE), A83) -> GAW CAPITAL ADVISORS LIMITED | I83: Microsoft Azure | M83: Admin: admin@gawcapitalaz.onmicrosoft.com | Q83: 43842 | S83: 44208 | T83: CL542691 | U83: 607148/1-2 | V83: 102540 | Y83: [12-Jan-2021] Tenant created and welcome letter sent. Completed order in CxS. | Z83: N
A84: Completed | D84: Daniel Yeung | E84: 31016889 / 98633579 | G84: CITYLINE (HONG KONG) LIMITED | H84: =IFERROR(VLOOKUP(G84, Sheet2!$A:$B, 2, FALSE), A84) -> CITYLINE (HONG KONG) LIMITED | I84: AWS (Amazon Web Service) | M84: Root Login :cartman.kh.lee@cityline.com.hk | O84: Address: 23/F, Legend Tower, 7 Shing Yip Street, Kwung Tong | Q84: 44274 | S84: 44273 | T84: CL546388 | U84: 860519 | V84: 102569 | Y84: Address: 23/F, Legend Tower, 7 Shing Yip Street, Kwung Tong [ 18-Mar-2021] AM Sammi provide root login. Pending for order no for completion, cus accepted invitation and pending for consumption to setup billing acc [22-Mar-2021] Checked consumption started on 19-Mar-2021. Pending for orer no for welcome letter and completion. [31-Mar-2021] Welcome letter sent. Pending for order reflected in CxS. [1-Apr-2021] Completed order in CxS with completion date on 18-MAr-2021 | Z84: N
A85: Cancelled | D85: Brian Yeung | E85: 22129233 / 60634889 | G85: UMADX ONLINE (MALAYSIA) SDN. BHD | H85: =IFERROR(VLOOKUP(G85, Sheet2!$A:$B, 2, FALSE), A85) -> UMADX ONLINE (MALAYSIA) SDN. BHD | I85: Microsoft Azure | M85: Tenant ID : umadxonline.onmicrosoft.com | Q85: 44300 | S85: 44417 | T85: CL540699 | U85: rn651683/1-2 | V85: 102572 | Y85: PS job only : Add on 1 x VM on existing cloud billing [12-Apr-2021] Passed order to PS team [9-Aug-2021] Sent email to Lok for status update. Lok updated that consultant informed him no PS is required. Asked Sales to cxl order in CxS. [04-Jan-2024] Confirmed with Lok no PS Job required. Close order in CxS | Z85: Y
A86: Completed | D86: Wendy Ho | E86: 2296 8966 / 5586 8792 | G86: CCC C262 PCCW Solutions Ltd C/O Hospital Authority | H86: =IFERROR(VLOOKUP(G86, Sheet2!$A:$B, 2, FALSE), A86) -> CCC C262 PCCW Solutions Ltd C/O Hospital Authority | I86: Microsoft Azure | M86: Cus email : wendy.sm.ho@pccw.com | Q86: 44302 | S86: 44298 | T86: CL542921 | U86: rn957422/1-2 | V86: 102574 | Y86: Cus email : wendy.sm.ho@pccw.com [12-Apr-2021] No need to create tenant. Closed order in CxS. | Z86: N
A87: Completed | D87: Tim NG | E87: 2783 2787 / 9662 5692 | F87: Email : tim.ng@lukfook.com | G87: Luk Fook Holdings Co Ltd | H87: =IFERROR(VLOOKUP(G87, Sheet2!$A:$B, 2, FALSE), A87) -> Luk Fook Holdings Co Ltd | I87: Alibaba Cloud | M87: Link email : alicloudga@jw28.com | O87: Address: 27/F, Metropole Square, 2 On Yiu Street, Shatin, NT | Q87: 44302 | S87: 44301 | T87: CL547225 | U87: rn 834282/1-2 | V87: 102576 | Y87: Address: 27/F, Metropole Square, 2 On Yiu Street, Shatin, NT Email : tim.ng@lukfook.com Remark: with Bdata b2b PS but still need to inform sales to ceate 2nd order [15-Apr-2021] Cus linked acc under HKT. Informed sales to issue PS order. Pending for order no. to close case. [16-Apr-2021] Order issued. Pending for order to reflect in CxS to close case and inform order team & sales for 2nd order creation. [19-Apr-2021] Completed order in CxS with completion date on 15-Apr-2021. | Z87: N
A88: Cancelled | D88: Tim NG | E88: 2783 2787 / 9662 5692 | G88: Luk Fook Holdings Co Ltd | H88: =IFERROR(VLOOKUP(G88, Sheet2!$A:$B, 2, FALSE), A88) -> Luk Fook Holdings Co Ltd | I88: Alibaba Cloud | Q88: 44302 | S88: NA | T88: Pending | U88: Pending | V88: Pending | Y88: Remark: PS job only. (refer to CL547225 [15-Apr-2021] Inform sales to issue 2nd PS job order. Pending for order no. [22-Jun-2021] email to sales Sammi for status ( thomas said not involved johnny's team lastly ) [22-Jun-2021] Thomas informed me that the PS job was handled by sercurity team finally instead. No PS job for our side. case cxl | Z88: Y
A89: Completed | D89: Mr. Jacky Hui | E89: 96742005 | G89: DDAAPP LIMITED | H89: =IFERROR(VLOOKUP(G89, Sheet2!$A:$B, 2, FALSE), A89) -> DDAAPP LIMITED | I89: AWS (Amazon Web Service) | Q89: 44319 | S89: 44300 | T89: CL548769 | U89: 444977/1-2 | V89: 102528 | Y89: Remark: PS job order only (Load Test $6,480). [ refer to CL548769] [27-Apr-2021] Informed by Thomas there is two PS jobs in total and one PS order is missing. PS job ( Load test UAT ) completed and UAT rec'd on 14-Apr-2021 together with 2nd PS job. Pending for order team to issue PS order in CxS and order can be completed once issue [29-Apr-2021] Orderissued & pending for order to reflect in system [12-Jul-2021] Completed order in System with completion & SRD on 3-May-2021 ( actually completion date on 14-Apr-2021) | Z89: Y
A90: Completed | D90: NA | E90: NA | G90: HKT ( Internal use ) | H90: =IFERROR(VLOOKUP(G90, Sheet2!$A:$B, 2, FALSE), A90) -> HKT ( Internal use ) | I90: Alibaba Cloud | M90: Alibaba UID: 460182270398259 Link email : hktali.taskforce@hkt-cloud.com | Q90: NA | S90: 44349 | T90: No record | U90: NA | V90: NA | Y90: [28-Apr-2021] Migration request from Zens to B-Data by Thomas ( For Internal use No order record ) [17-Jul-2021] Checked migration completed on 2-Jun-2021
A91: Completed | B91: New Install | D91: Jack | E91: 27860240 | F91: Jack.xiong@bacn.com.cn | G91: Bowker Asia Ltd (Win-Hanverky) | H91: =IFERROR(VLOOKUP(G91, Sheet2!$A:$B, 2, FALSE), A91) -> Bowker Asia Ltd (Win-Hanverky) | I91: Alibaba Cloud | K91: 5333230838981772 | M91: Alibaba UID : 5333230838981772 Root Email : hk.infra.support@win-hanverky.com.hk | O91: 6/F, BLK B, HK Spinners Ind Building, Phase 6,481-483 Castle Peak Road, Cheung Sha Wan, KLN | Q91: 45614 | R91: 45615 | S91: 45614 | T91: CL541610 | U91: RN 825521/1-2 | V91: 104056 | W91: UE24-00004918\1(OM) | X91: SD11702886 | Y91: [19-Nov-2024] Receive Order, CxS Complete Date : 18-Nov-2024. Create CL only, No need create Alibaba Account. [Kilson] | Z91: N | AA91: N | AB91: No | AC91: Kilson | AD91: http://10.10.10.209/OASIS_FILE_MANAGER/zip_files_download.php?qid=1327428&serialno=UE24-00004918&itemno=1&token=3fe28986e3408121df10cdcd105d2535
A92: Completed | D92: Victor Lee | E92: T: +852 2883 0323 | F92: Victor.PW.Lee@pccw.com | G92: HKTCSL 5G AR SERVICE | H92: =IFERROR(VLOOKUP(G92, Sheet2!$A:$B, 2, FALSE), A92) -> HKTCSL 5G AR SERVICE | I92: AWS (Amazon Web Service) | K92: 635921559641 | L92: gustolab | M92: 635921559641 Root Email : john.wong@thisisgusto.com | Q92: NA | S92: 44334 | T92: No record | U92: NA | V92: NA | Y92: Victor Lee T: +852 2883 0323 E: Victor.PW.Lee@pccw.com [28-Apr-2021] Migration request from eCloudvalley to ingram by Thomas [29-Apr-2021] Thomas updated that cus has accepted the invitation but checked that still can't find the cus in cloud checkr [18-May-2021] billing acc created. | Z92: N
A93: Completed | D93: Jack Leung | E93: 2610 8769 / 96023323 | G93: CHOW TAI FOOK JEWELLERY CO LTD (vcchoi) | H93: =IFERROR(VLOOKUP(G93, Sheet2!$A:$B, 2, FALSE), A93) -> CHOW TAI FOOK JEWELLERY CO LTD | I93: AWS (Amazon Web Service) | J93: 726125834629 | M93: Managed Service only | Q93: 44327 | S93: 44327 | T93: CL556466 | U93: 831955/1-2 | V93: 100580 | Y93: Remark: MS job only for AWS ID 757895108869 [10-May-2021] Passed case to T3 support team for MS onboardnig [9-Sep-2021] Completed order in CxS with SRD on 11-May-2021 | Z93: N | AA93: T3
A94: Completed | D94: benky chiu | E94: 36691865 / 9125 8138 | F94: Benkychiu@tps.cntaiping.com | G94: TAIPING SECURITIES (HK) CO LIMITED | H94: =IFERROR(VLOOKUP(G94, Sheet2!$A:$B, 2, FALSE), A94) -> TAIPING SECURITIES (HK) CO LIMITED | I94: Alibaba Cloud | M94: Alibaba Cloud root login email address : ishelpdesk@tps.cntaiping.com | Q94: 44348 | S94: 44349 | T94: CL541747 | U94: 040360/1-2 | V94: 102584 | Y94: Contact email : Benkychiu@tps.cntaiping.com [18-May-2021] Submit migration request to Bdata. Pending for reply ( ~2 weeks ) [26-May-2021] Email to support for status update [1-Jun-2021] email to support for status update again. [2-Jun-2021] Grouping under HKT completed. completed order in CxS. Welcome letter sent | Z94: N
A95: Completed | D95: Calven Wong | E95: 2888 7333 | G95: HKT Teleservice Ltd (Prod) RENAME in CloudCheckr HKT Teleservice International Ltd (Prod) | H95: =IFERROR(VLOOKUP(G95, Sheet2!$A:$B, 2, FALSE), A95) -> HKT TELESERVICE INTERNATIONAL LTD (PROD) | I95: AWS (Amazon Web Service) | K95: 521618880771 | L95: calven.ch.wong | M95: AWS ID: 521618880771 Root Login: calven.ch.wong@pccw.com | O95: Address: BPF 13 | Q95: NA | S95: 44337 | T95: NA | U95: NA | V95: NA | Y95: Remark : For HKT internal use. Address: BPF 13 [17-May-2021] Submit request to ingram and pending for linkage [18-May-2021] Invitation sent. [22-May-2021]Checked acc joined on 21-May-2021. Billing acc created on 22-May-2021. No welcome letter [15-Jun-2021] Thomas informed that the company named is changed to HKT Teleservice International Ltd (Prod) | Z95: N
A96: Completed | D96: Ken Kwok | E96: 2888 5404 | G96: HKT Teleservice Ltd (Dev) RENAME in CloudCheckr HKT Teleservice International Ltd (Dev) | H96: =IFERROR(VLOOKUP(G96, Sheet2!$A:$B, 2, FALSE), A96) -> HKT TELESERVICE INTERNATIONAL LTD (DEV) | I96: AWS (Amazon Web Service) | K96: 851055693828 | L96: KenKwok | M96: AWS ID: 851055693828 Root Login: ken.cf.kwok@pccw.com | O96: Address: BPF 13 | Q96: NA | S96: 44401 | T96: NA | U96: NA | V96: NA | Y96: Address: BPF 13 [17-May-2021] Submit request to ingram and pending for linkage [24-May-2021] still pending for usage to create billing portal . [15-Jun-2021] Thomas informed that the company named should be HKT Teleservice International Ltd [27-Jul-2021] checked acc joined on 24-Jul-2021. Billing acc created on 27-Jul-2021. No Welcome letter. | Z96: N
A97: Cancelled | D97: Angus Lau/ Kelvin Ng | E97: 3972 0701 / 3972 0780 6083 0014 / 6977 1055 | F97: kelvinng@heungkongfinnancial.com / auguslau@heungkongfinancial.com | G97: TECKLE SOLUTIONS LIMITED | H97: =IFERROR(VLOOKUP(G97, Sheet2!$A:$B, 2, FALSE), A97) -> TECKLE SOLUTIONS LIMITED | I97: Alibaba Cloud | M97: Link email : 1690stock_app@heungkongfinancial.com | Q97: 44340 | T97: CL553989 | U97: 341916/1-2 | V97: 102588 | Y97: Contact : kelvinng@heungkongfinnancial.com / auguslau@heungkongfinancial.com [22-May-2021] Submit migration request to Bdata. Pending for reply ( ~2 weeks ) [1-Jun-2021] email to support for status update. [15-Jun-2021] Seems the target consumption does not meet the basic requirement. May have to withdraw the order [12-Nov-2021] Sent email to Krad for status update and confirm. [11-Jan-2024] Order Cancelled | Z97: N
A98: Completed | D98: wai chung | E98: 2610 8769 / 90323685 | F98: cus email:waichung@chowtaifook.com | G98: CHOW TAI FOOK JEWELLERY CO LTD | H98: =IFERROR(VLOOKUP(G98, Sheet2!$A:$B, 2, FALSE), A98) -> CHOW TAI FOOK JEWELLERY CO LTD | I98: AWS (Amazon Web Service) | J98: 726125834629 | M98: Acc name : HKT Chow Tai Fook Jewellery Co Ltd 805193327859 ( create by KCY for gravity project but tony said cus will create their own. Can this AWS ID be ignore / delete? ) root email : ctfhkt@hkt-cloud.com PW: Ctfhkt_cus006 | Q98: 44351 | S98: 44670 | T98: CL557522 | U98: 669199/1-2 | V98: 102954 | Y98: Remark: PS job ( $ 47,520 ) only Gravity Deployment UAT + production (cus email:waichung@chowtaifook.com) [31-May-2021] Passed case to johnny's team and T3 support team submit request to ingram. Pending for linking [31-May-2021] Tony Tso request withdraw linking request as cus will create their own AWS master acc and will then group the existing acc under their master acc instead of HKT. which mean this one is only PS job order. [9-Sep-2021] A CloudChekcr admin acc was created to T3 STanley for their MS role [15-Sep-2021] Lok updated that still pending for cus input to proceed the PS job. [19-Apr-2022] Thomas informed that the PS job has been completed. Asking Lok for the UAT. Completed CxS order with SRD on 19-Apr-2022. | Z98: Y | AA98: N
A99: Completed | D99: No record | E99: TBC | G99: No record | H99: =IFERROR(VLOOKUP(G99, Sheet2!$A:$B, 2, FALSE), A99) -> No record | I99: Alibaba Cloud | M99: Alibaba UID : 5460182270398259 Link email : hktali.taskforce@hkt-cloud.com | Q99: No record | S99: 44349 | T99: No record | U99: No record | V99: No record | Y99: [28-Apr-2021] Migration request from Zens to B-Data by Thomas [2-Jun-2021] Migration done on 2-Jun-2021. | Z99: N
A100: Completed | G100: CAM 8 PCCW (Macau) Ltd c/o SJM | H100: =IFERROR(VLOOKUP(G100, Sheet2!$A:$B, 2, FALSE), A100) -> CAM 8 PCCW (Macau) Ltd c/o SJM | I100: Alibaba Cloud | M100: Alibaba UID : 5913782617694384 Link email : itsoc@macausjm-glp.com This customer UID is under "HKT-Macau/Bdata Main Account" | T100: No record | U100: No record | V100: No record | Y100: Account creation not handled by SP team. [28-Apr-2021] Migration request to Bdata on 28-Apr-2021 by thomas [17-Jul-2021] Bdata updated that migration completed but not reflected in portal | Z100: N | AA100: NA
...

Sheet Sheet2
A1: Company Name | B1: Standardized
A2: WING FUNG REALTY INVESTMENT LIMITED | B2: WING FUNG REALTY INVESTMENT LIMITED
A3: WING FUNG PRECIOUS METALS LIMITED | B3: WING FUNG PRECIOUS METALS LIMITED
A4: WING FUNG FUTURES LIMITED | B4: WING FUNG FUTURES LIMITED
A5: WING FUNG BULLION INVESTMENT LIMITED | B5: WING FUNG BULLION INVESTMENT LIMITED
A6: UMADX ONLINE (MALAYSIA) SDN. BHD | B6: UMADX ONLINE (MALAYSIA) SDN. BHD
A7: TYSAN MANAGEMENT LIMITED | B7: TYSAN MANAGEMENT LIMITED
A8: TRAVELSKY TECHNOLOGY (HONGKONG) LTD. | B8: TRAVELSKY TECHNOLOGY (HONGKONG) LTD.
A9: Techtronic Industries Co. Ltd | B9: Techtronic Industries Co. Ltd
A10: SOFI SECURITIES LIMITED (SOFI SERVICES ( HONG KONG ) LTD) | B10: SOFI SECURITIES LIMITED (SOFI SERVICES ( HONG KONG ) LTD)
A11: PROFIT CHART DEVELOPMENT LIMITED | B11: PROFIT CHART DEVELOPMENT LIMITED
A12: ORANGE DATA LIMITED (Chnaged ASCENTAS CAPITAL MANAGEMENT LIMITED) | B12: ASCENTAS CAPITAL MANAGEMENT LIMITED
... A209: CAM 8_HKT GenAI Demo Platform | B209: CAM 8_HKT GenAI Demo Platform
